sonicare_ble/__init__.py
sonicare_ble/parser.py
sonicare_ble/py.typed
sonicare_ble-0.0.1.dist-info/METADATA
sonicare_ble-0.0.1.dist-info/WHEEL
sonicare_ble-0.0.1.dist-info/LICENSE
sonicare_ble-0.0.1.dist-info/RECORD
